README.md
setup.py
dumbtext/__init__.py
dumbtext/text.py
dumbtext.egg-info/PKG-INFO
dumbtext.egg-info/SOURCES.txt
dumbtext.egg-info/dependency_links.txt
dumbtext.egg-info/entry_points.txt
dumbtext.egg-info/requires.txt
dumbtext.egg-info/top_level.txt
dumbtext.egg-info/zip-safe