Metadata-Version: 2.1
Name: dumbtext
Version: 0.0.1
Summary: A set of basic functions for quickly saving and loading textfiles.
Home-page: https://github.com/josharnoldjosh/EasyText.git
Author: Josh Arnold
Author-email: jarnold@ucdavis.edu
License: UNKNOWN
Platform: UNKNOWN
Classifier: License :: OSI Approved :: GNU General Public License v3 (GPLv3)
Classifier: Operating System :: OS Independent
Classifier: Programming Language :: Python
Classifier: Programming Language :: Python :: 3
Classifier: Programming Language :: Python :: 3.4
Classifier: Programming Language :: Python :: 3.5
Classifier: Programming Language :: Python :: 3.6
Classifier: Topic :: Software Development :: Libraries :: Python Modules
Classifier: Natural Language :: English
